staplelib/__init__.py
staplelib/commands.py
staplelib/iohelper.py
staplelib/stapler.py
staplelib/tests.py
stapler-0.3.3.dist-info/DESCRIPTION.rst
stapler-0.3.3.dist-info/METADATA
stapler-0.3.3.dist-info/RECORD
stapler-0.3.3.dist-info/WHEEL
stapler-0.3.3.dist-info/entry_points.txt
stapler-0.3.3.dist-info/metadata.json
stapler-0.3.3.dist-info/top_level.txt
