Metadata-Version: 2.0
Name: stapler
Version: 0.3.3
Summary: Manipulate PDF documents from the command line
Home-page: https://github.com/hellerbarde/stapler
Author: Philip Stark, Fred Wenzel
Author-email: git@codechaos.ch
License: UNKNOWN
Keywords: pdf utility cli concatenate tool
Platform: UNKNOWN
Classifier: Development Status :: 5 - Production/Stable
Classifier: Programming Language :: Python :: 2
Classifier: Intended Audience :: Science/Research
Classifier: Topic :: Utilities
Classifier: License :: OSI Approved :: BSD License
Requires-Dist: PyPDF2 (>=1.24)
